ShortJob/GetResult.py
ShortJob/MkJob.py
ShortJob/MkMulJob.py
ShortJob/__init__.py
ShortJob/command.py
ShortJob-1.8.dist-info/LICENSE
ShortJob-1.8.dist-info/METADATA
ShortJob-1.8.dist-info/WHEEL
ShortJob-1.8.dist-info/top_level.txt
ShortJob-1.8.dist-info/RECORD
