Metadata-Version: 2.1
Name: ShortJob
Version: 1.8
Summary: Multitask Multilanguage
Home-page: UNKNOWN
Author: Xin-Xin Ma
License: UNKNOWN
Project-URL: Source, https://github.com/xxmawhu/ShortJob
Platform: UNKNOWN
